unifi_backup/__init__.py
unifi_backup/__main__.py
unifi_backup/cli.py
unifi_backup-0.2.2.dist-info/LICENSE
unifi_backup-0.2.2.dist-info/METADATA
unifi_backup-0.2.2.dist-info/WHEEL
unifi_backup-0.2.2.dist-info/entry_points.txt
unifi_backup-0.2.2.dist-info/top_level.txt
unifi_backup-0.2.2.dist-info/RECORD
