Metadata-Version: 2.1
Name: unifi_backup
Version: 0.2.2
Summary: A simple tool to fetch backups from the UniFi Network Application
Author-email: Stanislav Meduna <stano@meduna.org>
Project-URL: Homepage, https://github.com/numo68/unifi-backup
Project-URL: Bug Tracker, https://github.com/numo68/unifi-backup/issues
Classifier: Programming Language :: Python :: 3
Classifier: License :: OSI Approved :: MIT License
Classifier: Operating System :: OS Independent
Requires-Python: >=3.10
License-File: LICENSE
Requires-Dist: PyYAML
Requires-Dist: schema
Requires-Dist: pyunifi
Requires-Dist: urllib3
Requires-Dist: prometheus-client
